aiomeilisearch/__init__.py
aiomeilisearch/__version__.py
aiomeilisearch/_http_client.py
aiomeilisearch/client.py
aiomeilisearch/config.py
aiomeilisearch/document.py
aiomeilisearch/error.py
aiomeilisearch/index.py
aiomeilisearch/index_setting.py
aiomeilisearch-1.0.1.dist-info/LICENSE
aiomeilisearch-1.0.1.dist-info/METADATA
aiomeilisearch-1.0.1.dist-info/WHEEL
aiomeilisearch-1.0.1.dist-info/top_level.txt
aiomeilisearch-1.0.1.dist-info/RECORD
