Metadata-Version: 2.1
Name: aiomeilisearch
Version: 1.0.1
Summary: The MeiliSearch API asyncio client for Python
Home-page: https://github.com/ziyoubaba/aiomeilisearch
Author: ziyoubaba
Author-email: 1258843771@qq.com
License: UNKNOWN
Platform: UNKNOWN
Classifier: Programming Language :: Python :: 3
Classifier: License :: OSI Approved :: MIT License
Classifier: Operating System :: OS Independent
Requires-Dist: aiohttp
